MANIFEST.in
README.rst
requirements.txt
setup.cfg
setup.py
src/flask_social_blueprint/__init__.py
src/flask_social_blueprint/core.py
src/flask_social_blueprint/providers.py
src/flask_social_blueprint/tests.py
src/flask_social_blueprint.egg-info/PKG-INFO
src/flask_social_blueprint.egg-info/SOURCES.txt
src/flask_social_blueprint.egg-info/dependency_links.txt
src/flask_social_blueprint.egg-info/requires.txt
src/flask_social_blueprint.egg-info/top_level.txt