Metadata-Version: 1.1
Name: flask-social-blueprint
Version: 0.7.2
Summary: An OAuth based authentication blueprint for flask. Easy to extend and override
Home-page: https://github.com/wooyek/flask-social-blueprint
Author: Janusz Skonieczny
Author-email: js@bravelabs.pl
License: MIT
Keywords: flask social oauth authentication
Platform: UNKNOWN
Classifier: Programming Language :: Python
Classifier: Development Status :: 4 - Beta
Classifier: Natural Language :: English
Classifier: Environment :: Web Environment
Classifier: Intended Audience :: Developers
Classifier: License :: OSI Approved :: MIT License
Classifier: Operating System :: OS Independent
Classifier: Topic :: Software Development :: Libraries :: Python Modules
Classifier: Topic :: Software Development :: Libraries :: Application Frameworks
Classifier: Topic :: Internet :: WWW/HTTP :: Dynamic Content
